LICENSE
README.md
autoflake.py
test_autoflake.py
autoflake-2.1.0.dist-info/METADATA
autoflake-2.1.0.dist-info/WHEEL
autoflake-2.1.0.dist-info/entry_points.txt
autoflake-2.1.0.dist-info/licenses/AUTHORS.rst
autoflake-2.1.0.dist-info/licenses/LICENSE
autoflake-2.1.0.dist-info/RECORD
