Metadata-Version: 2.1
Name: autoflake
Version: 2.1.0
Summary: Removes unused imports and unused variables
Project-URL: Homepage, https://www.github.com/PyCQA/autoflake
License: MIT
License-File: AUTHORS.rst
License-File: LICENSE
Keywords: automatic,clean,fix,import,unused
Classifier: Environment :: Console
Classifier: Intended Audience :: Developers
Classifier: License :: OSI Approved :: MIT License
Classifier: Programming Language :: Python :: 3
Classifier: Programming Language :: Python :: 3 :: Only
Classifier: Topic :: Software Development :: Quality Assurance
Requires-Python: >=3.7
Requires-Dist: pyflakes>=3.0.0
Requires-Dist: tomli>=2.0.1; python_version < '3.11'
